starter.v
/**
* starter.v
*
* Serial Peripheral Interface (SPI)
*
* Implement both sides of a SPI interface.
*
*/

module master_device(DATA_ADDR, SS_ADDR, SCLK, MOSI, MISO, SS);
// I/O PORTS (DO NOT MODIFY)
input         MISO;
output        MOSI, SCLK;
input   [1:0] SS_ADDR;
output  reg [3:0] SS;
input   [7:0] DATA_ADDR;

reg [7:0] DATA;
reg [7:0] tempData;

// ADD COMBINATIONAL LOGIC HERE
reg SCLK;
reg MOSI = 1;

integer i;
integer dataSize = 0;


always@(DATA_ADDR, SS_ADDR)
begin
  // ADD SEQUENTIAL LOGIC HERE
  MOSI = 1;
  SCLK = 1;
  if(SS_ADDR == 3'd0)begin
    SS = 4'b0111;
    for(i = 0; i < 64; i = i + 1)begin
      if(i < 8)begin
        MOSI = DATA_ADDR[i];
      end
      SCLK = !SCLK;
      #1;
      tempData[dataSize] = MISO;
      if(SCLK == 1) begin
        dataSize = dataSize + 1;
        if(dataSize == 8)begin
          dataSize = 0;
          DATA = tempData;
          tempData = 8'b00000000;
          #480;
        end
      end
    end
  end
  else if(SS_ADDR == 3'd1)begin
    SS = 4'b1011;
    for(i = 0; i < 64; i = i + 1)begin
      if(i < 8)begin
        MOSI = DATA_ADDR[i];
      end
      SCLK = !SCLK;
      #1;
      tempData[dataSize] = MISO;
      if(SCLK == 1) begin
        dataSize = dataSize + 1;
        if(dataSize == 8)begin
          dataSize = 0;
          DATA = tempData;
          tempData = 8'b00000000;
          #480;
        end
      end
    end
  end
  else if(SS_ADDR == 3'd2)begin
    SS = 4'b1101;
    for(i = 0; i < 64; i = i + 1)begin
      if(i < 8)begin
        MOSI = DATA_ADDR[i];
      end
      SCLK = !SCLK;
      #1;
      tempData[dataSize] = MISO;
      if(SCLK == 1) begin
        dataSize = dataSize + 1;
        if(dataSize == 8)begin
          dataSize = 0;
          DATA = tempData;
          tempData = 8'b00000000;
          #480;
        end
      end
    end
  end
  else if(SS_ADDR == 3'd3)begin
    SS = 4'b1110;
    for(i = 0; i < 64; i = i + 1)begin
      if(i < 8)begin
        MOSI = DATA_ADDR[i];
      end
      SCLK = !SCLK;
      #1;
      tempData[dataSize] = MISO;
      if(SCLK == 1) begin
        dataSize = dataSize + 1;
        if(dataSize == 8)begin
          dataSize = 0;
          DATA = tempData;
          tempData = 8'b00000000;
          #480;
        end
      end
    end
  end
end

endmodule

module slave_device(SCLK, MOSI, MISO, SS);
// I/O PORTS (DO NOT MODIFY)
input       MOSI, SCLK, SS;
output reg MISO;


// INTERNAL DATA REGISTERS (DO NOT MODIFY)
reg [7:0] reg0 = 8'h41; // Address = 8'h1A
reg [7:0] reg1 = 8'hDC; // Address = 8'h1B
reg [7:0] reg2 = 8'h3B; // Address = 8'h1C
reg [7:0] reg3 = 8'h4E; // Address = 8'h1D
reg [7:0] reg4 = 8'h8C; // Address = 8'h2A
reg [7:0] reg5 = 8'hB5; // Address = 8'h2B
reg [7:0] reg6 = 8'h05; // Address = 8'h2C
reg [7:0] reg7 = 8'hE5; // Address = 8'h2D

// ADD YOUR CODE HERE
initial MISO = 0;

reg [7:0] dataItem = 8'h41;
reg [7:0] lastData;
integer checkedBit = 0;
always @(posedge SCLK)
begin
  MISO = 0;
  if(SS == 0) begin
    if (checkedBit > 7) begin
      checkedBit = 0;
      if(dataItem == reg0) begin
        dataItem = reg1;
      end
      else if(dataItem == reg1) begin
        dataItem = reg2;
      end
      else if(dataItem == reg2) begin
        dataItem = reg3;
      end
      else if(dataItem == reg3) begin
        dataItem = reg4;
      end
      else if(dataItem == reg4) begin
        dataItem = reg5;
      end
      else if(dataItem == reg5) begin
        dataItem = reg6;
      end
      else if(dataItem == reg6) begin
        dataItem = reg7;
      end
      else if(dataItem == reg6) begin
        dataItem = reg0;
      end
    end
    MISO = dataItem[checkedBit];
    lastData[checkedBit] = MISO;
    checkedBit = checkedBit + 1;
  end
end

endmodule

testbench.v
`timescale  1ns/1ns
`include    "starter.v"

module testbench;
reg [1:0] SS_ADDR   = 0;
reg [7:0] DATA_ADDR = 0;

wire [3:0] SS;
wire MISO, MOSI, SCLK;
wire MISO_w0, MISO_w1, MISO_w2, MISO_w3;

assign MISO = MISO_w0 | MISO_w1 | MISO_w2 | MISO_w3;

master_device UUTM0(.DATA_ADDR(DATA_ADDR), .SS_ADDR(SS_ADDR), .SCLK(SCLK), .MOSI(MOSI), .MISO(MISO), .SS(SS));

slave_device UUTS0(.SCLK(SCLK), .MOSI(MOSI), .MISO(MISO_w0), .SS(SS[0]));
slave_device UUTS1(.SCLK(SCLK), .MOSI(MOSI), .MISO(MISO_w1), .SS(SS[1]));
slave_device UUTS2(.SCLK(SCLK), .MOSI(MOSI), .MISO(MISO_w2), .SS(SS[2]));
slave_device UUTS3(.SCLK(SCLK), .MOSI(MOSI), .MISO(MISO_w3), .SS(SS[3]));

integer pass = 0;
integer cases = 0;
integer i = 0;
integer j = 0;

reg [7:0] addresses [7:0];
reg [7:0] testCases [7:0];

initial begin
  // Generate a waveform file.
  $dumpfile("SPI.vcd");
  $dumpvars(0, testbench);

  // Load the addresses into the array.
  addresses[0] = 8'h1A;
  addresses[1] = 8'h1B;
  addresses[2] = 8'h1C;
  addresses[3] = 8'h1D;
  addresses[4] = 8'h2A;
  addresses[5] = 8'h2B;
  addresses[6] = 8'h2C;
  addresses[7] = 8'h2D;

  // Load the test cases into the array.
  testCases[0] = 8'h41;
  testCases[1] = 8'hDC;
  testCases[2] = 8'h3B;
  testCases[3] = 8'h4E;
  testCases[4] = 8'h8C;
  testCases[5] = 8'hB5;
  testCases[6] = 8'h05;
  testCases[7] = 8'hE5;

  // Execute the test.
  for (i = 0; i < 4; i = i + 1)
  begin
    for (j = 0; j < 8; j = j + 1)
    begin
    cases = cases + 1;
      SS_ADDR = i; DATA_ADDR = addresses[j]; #500;
      if (UUTM0.DATA == testCases[j])
      begin
        $display("Retrieved data from device %d = %h. (PASS)", i, UUTM0.DATA);
        pass = pass + 1;
      end
      else
      begin
        $display("Retrieved data from device %d = %h. (FAIL)", i, UUTM0.DATA);
      end
    end
  end
  $display("Test complete with %d of %d test cases passing.", pass, cases);
  $finish;
end
endmodule

SPI.vcd
$date
	Fri May  8 17:29:35 2020
$end
$version
	Icarus Verilog
$end
$timescale
	1ns
$end
$scope module testbench $end
$var wire 1 ! MISO $end
$var wire 4 " SS [3:0] $end
$var wire 1 # SCLK $end
$var wire 1 $ MOSI $end
$var wire 1 % MISO_w3 $end
$var wire 1 & MISO_w2 $end
$var wire 1 ' MISO_w1 $end
$var wire 1 ( MISO_w0 $end
$var reg 8 ) DATA_ADDR [7:0] $end
$var reg 2 * SS_ADDR [1:0] $end
$var integer 32 + cases [31:0] $end
$var integer 32 , i [31:0] $end
$var integer 32 - j [31:0] $end
$var integer 32 . pass [31:0] $end
$scope module UUTM0 $end
$var wire 8 / DATA_ADDR [7:0] $end
$var wire 1 ! MISO $end
$var wire 2 0 SS_ADDR [1:0] $end
$var reg 8 1 DATA [7:0] $end
$var reg 1 $ MOSI $end
$var reg 1 # SCLK $end
$var reg 4 2 SS [3:0] $end
$var reg 8 3 tempData [7:0] $end
$var integer 32 4 dataSize [31:0] $end
$var integer 32 5 i [31:0] $end
$upscope $end
$scope module UUTS0 $end
$var wire 1 $ MOSI $end
$var wire 1 # SCLK $end
$var wire 1 6 SS $end
$var reg 1 ( MISO $end
$var reg 8 7 dataItem [7:0] $end
$var reg 8 8 lastData [7:0] $end
$var reg 8 9 reg0 [7:0] $end
$var reg 8 : reg1 [7:0] $end
$var reg 8 ; reg2 [7:0] $end
$var reg 8 < reg3 [7:0] $end
$var reg 8 = reg4 [7:0] $end
$var reg 8 > reg5 [7:0] $end
$var reg 8 ? reg6 [7:0] $end
$var reg 8 @ reg7 [7:0] $end
$var integer 32 A checkedBit [31:0] $end
$upscope $end
$scope module UUTS1 $end
$var wire 1 $ MOSI $end
$var wire 1 # SCLK $end
$var wire 1 B SS $end
$var reg 1 ' MISO $end
$var reg 8 C dataItem [7:0] $end
$var reg 8 D lastData [7:0] $end
$var reg 8 E reg0 [7:0] $end
$var reg 8 F reg1 [7:0] $end
$var reg 8 G reg2 [7:0] $end
$var reg 8 H reg3 [7:0] $end
$var reg 8 I reg4 [7:0] $end
$var reg 8 J reg5 [7:0] $end
$var reg 8 K reg6 [7:0] $end
$var reg 8 L reg7 [7:0] $end
$var integer 32 M checkedBit [31:0] $end
$upscope $end
$scope module UUTS2 $end
$var wire 1 $ MOSI $end
$var wire 1 # SCLK $end
$var wire 1 N SS $end
$var reg 1 & MISO $end
$var reg 8 O dataItem [7:0] $end
$var reg 8 P lastData [7:0] $end
$var reg 8 Q reg0 [7:0] $end
$var reg 8 R reg1 [7:0] $end
$var reg 8 S reg2 [7:0] $end
$var reg 8 T reg3 [7:0] $end
$var reg 8 U reg4 [7:0] $end
$var reg 8 V reg5 [7:0] $end
$var reg 8 W reg6 [7:0] $end
$var reg 8 X reg7 [7:0] $end
$var integer 32 Y checkedBit [31:0] $end
$upscope $end
$scope module UUTS3 $end
$var wire 1 $ MOSI $end
$var wire 1 # SCLK $end
$var wire 1 Z SS $end
$var reg 1 % MISO $end
$var reg 8 [ dataItem [7:0] $end
$var reg 8 \ lastData [7:0] $end
$var reg 8 ] reg0 [7:0] $end
$var reg 8 ^ reg1 [7:0] $end
$var reg 8 _ reg2 [7:0] $end
$var reg 8 ` reg3 [7:0] $end
$var reg 8 a reg4 [7:0] $end
$var reg 8 b reg5 [7:0] $end
$var reg 8 c reg6 [7:0] $end
$var reg 8 d reg7 [7:0] $end
$var integer 32 e checkedBit [31:0] $end
$upscope $end
$upscope $end
$enddefinitions $end
#0
$dumpvars
b0 e
b11100101 d
b101 c
b10110101 b
b10001100 a
b1001110 `
b111011 _
b11011100 ^
b1000001 ]
bx \
b1000001 [
0Z
b0 Y
b11100101 X
b101 W
b10110101 V
b10001100 U
b1001110 T
b111011 S
b11011100 R
b1000001 Q
bx P
b1000001 O
1N
b0 M
b11100101 L
b101 K
b10110101 J
b10001100 I
b1001110 H
b111011 G
b11011100 F
b1000001 E
bx D
b1000001 C
1B
b0 A
b11100101 @
b101 ?
b10110101 >
b10001100 =
b1001110 <
b111011 ;
b11011100 :
b1000001 9
bx 8
b1000001 7
16
b0 5
b0 4
bx 3
b111 2
bx 1
b0 0
b11010 /
b0 .
b0 -
b0 ,
b1 +
b0 *
b11010 )
0(
0'
0&
0%
0$
0#
b111 "
0!
$end
#1
1!
b1 e
bx1 \
1%
1#
1$
b1 5
bx0 3
#2
0#
0$
b10 5
b1 4
bx1 3
#3
0!
b10 e
bx01 \
0%
1#
1$
b11 5
bx11 3
#4
0#
b100 5
b10 4
bx01 3
#5
b11 e
bx001 \
1#
0$
b101 5
bx001 3
#6
0#
b110 5
b11 4
#7
b100 e
bx0001 \
1#
b111 5
bx0001 3
#8
0#
b1000 5
b100 4
#9
b101 e
bx00001 \
1#
b1001 5
bx00001 3
#10
0#
b1010 5
b101 4
#11
b110 e
bx000001 \
1#
b1011 5
bx000001 3
#12
0#
b1100 5
b110 4
#13
1!
b111 e
bx1000001 \
1%
1#
b1101 5
bx0000001 3
#14
0#
b1110 5
b111 4
bx1000001 3
#15
0!
b1000 e
b1000001 \
0%
1#
b1111 5
b11000001 3
#16
b1000001 1
b0 4
b0 3
#496
0#
b10000 5
#497
b1000000 \
b11011100 [
b1 e
1#
b10001 5
#498
0#
b10010 5
b1 4
#499
b10 e
1#
b10011 5
#500
0#
b10100 5
b10 4
b11011 )
b11011 /
b10 +
b1 -
b1 .
#501
1!
b11 e
b1000100 \
1%
1#
b10101 5
#502
0#
b10110 5
b11 4
b100 3
#503
b100 e
b1001100 \
1%
1#
b10111 5
b1100 3
#504
0#
b11000 5
b100 4
#505
b101 e
b1011100 \
1%
1#
b11001 5
b11100 3
#506
0#
b11010 5
b101 4
#507
0!
b110 e
0%
1#
b11011 5
b111100 3
#508
0#
b11100 5
b110 4
b11100 3
#509
1!
b111 e
1%
1#
b11101 5
#510
0#
b11110 5
b111 4
b1011100 3
#511
b1000 e
b11011100 \
1%
1#
b11111 5
b11011100 3
#512
b0 3
b11011100 1
b0 4
#992
0#
b100000 5
#993
b11011101 \
b111011 [
b1 e
1%
1#
b100001 5
b1 3
#994
0#
b100010 5
b1 4
#995
b10 e
b11011111 \
1%
1#
b100011 5
b11 3
#996
0#
b100100 5
b10 4
#997
0!
b11 e
b11011011 \
0%
1#
b100101 5
b111 3
#998
0#
b100110 5
b11 4
b11 3
#999
1!
b100 e
1%
1#
b100111 5
#1000
0#
b101000 5
b100 4
b1011 3
b11100 )
b11100 /
b11 +
b10 -
b10 .
#1001
b101 e
1%
1#
b101001 5
b11011 3
#1002
0#
b101010 5
b101 4
#1003
b110 e
b11111011 \
1%
1#
b101011 5
b111011 3
#1004
0#
b101100 5
b110 4
#1005
0!
b111 e
b10111011 \
0%
1#
b101101 5
b1111011 3
#1006
0#
b101110 5
b111 4
b111011 3
#1007
b1000 e
b111011 \
1#
b101111 5
#1008
b0 3
b111011 1
b0 4
#1488
0#
b110000 5
#1489
b111010 \
b1001110 [
b1 e
1#
b110001 5
#1490
0#
b110010 5
b1 4
#1491
1!
b10 e
1%
1#
b110011 5
#1492
0#
b110100 5
b10 4
b10 3
#1493
b11 e
b111110 \
1%
1#
b110101 5
b110 3
#1494
0#
b110110 5
b11 4
#1495
b100 e
1%
1#
b110111 5
b1110 3
#1496
0#
b111000 5
b100 4
#1497
0!
b101 e
b101110 \
0%
1#
b111001 5
b11110 3
#1498
0#
b111010 5
b101 4
b1110 3
#1499
b110 e
b1110 \
1#
b111011 5
#1500
0#
b111100 5
b110 4
b11101 )
b11101 /
b100 +
b11 -
b11 .
#1501
1!
b111 e
b1001110 \
1%
1#
b111101 5
#1502
0#
b111110 5
b111 4
b1001110 3
#1503
0!
b1000 e
0%
1#
b111111 5
b11001110 3
#1504
b1001110 1
b0 4
b0 3
#1984
b1000000 5
#2000
0#
b0 5
0$
b101010 )
b101010 /
b101 +
b100 -
b100 .
#2001
b10001100 [
b1 e
1#
1$
b1 5
#2002
0#
0$
b10 5
b1 4
#2003
b10 e
b1001100 \
1#
1$
b11 5
#2004
0#
0$
b100 5
b10 4
#2005
1!
b11 e
1%
1#
1$
b101 5
#2006
0#
0$
b110 5
b11 4
b100 3
#2007
b100 e
1%
1#
b111 5
b1100 3
#2008
0#
b1000 5
b100 4
#2009
0!
b101 e
0%
1#
b1001 5
b11100 3
#2010
0#
b1010 5
b101 4
b1100 3
#2011
b110 e
1#
b1011 5
#2012
0#
b1100 5
b110 4
#2013
b111 e
b1100 \
1#
b1101 5
#2014
0#
b1110 5
b111 4
#2015
1!
b1000 e
b10001100 \
1%
1#
b1111 5
#2016
b10001100 1
b0 4
b0 3
#2496
0#
b10000 5
#2497
b10001101 \
b10110101 [
b1 e
1%
1#
b10001 5
b1 3
#2498
0#
b10010 5
b1 4
#2499
0!
b10 e
0%
1#
b10011 5
b11 3
#2500
0#
b10100 5
b10 4
b1 3
b101011 )
b101011 /
b110 +
b101 -
b101 .
#2501
1!
b11 e
1%
1#
b10101 5
#2502
0#
b10110 5
b11 4
b101 3
#2503
0!
b100 e
b10000101 \
0%
1#
b10111 5
b1101 3
#2504
0#
b11000 5
b100 4
b101 3
#2505
1!
b101 e
b10010101 \
1%
1#
b11001 5
#2506
0#
b11010 5
b101 4
b10101 3
#2507
b110 e
b10110101 \
1%
1#
b11011 5
b110101 3
#2508
0#
b11100 5
b110 4
#2509
0!
b111 e
0%
1#
b11101 5
b1110101 3
#2510
0#
b11110 5
b111 4
b110101 3
#2511
1!
b1000 e
1%
1#
b11111 5
#2512
b10110101 1
b0 4
b0 3
#2992
0#
b100000 5
#2993
b101 [
b1 e
1%
1#
b100001 5
b1 3
#2994
0#
b100010 5
b1 4
#2995
0!
b10 e
0%
1#
b100011 5
b11 3
#2996
0#
b100100 5
b10 4
b1 3
#2997
1!
b11 e
1%
1#
b100101 5
#2998
0#
b100110 5
b11 4
b101 3
#2999
0!
b100 e
0%
1#
b100111 5
b1101 3
#3000
0#
b101000 5
b100 4
b101 3
b101100 )
b101100 /
b111 +
b110 -
b110 .
#3001
b101 e
b10100101 \
1#
b101001 5
#3002
0#
b101010 5
b101 4
#3003
b110 e
b10000101 \
1#
b101011 5
#3004
0#
b101100 5
b110 4
#3005
b111 e
1#
b101101 5
#3006
0#
b101110 5
b111 4
#3007
b1000 e
b101 \
1#
b101111 5
#3008
b0 3
b101 1
b0 4
#3488
0#
b110000 5
#3489
1!
1%
b11100101 [
b1 e
1#
b110001 5
#3490
0#
b110010 5
b1 4
b1 3
#3491
0!
b10 e
0%
1#
b110011 5
b11 3
#3492
0#
b110100 5
b10 4
b1 3
#3493
1!
b11 e
1%
1#
b110101 5
#3494
0#
b110110 5
b11 4
b101 3
#3495
0!
b100 e
0%
1#
b110111 5
b1101 3
#3496
0#
b111000 5
b100 4
b101 3
#3497
b101 e
1#
b111001 5
#3498
0#
b111010 5
b101 4
#3499
1!
b110 e
b100101 \
1%
1#
b111011 5
#3500
0#
b111100 5
b110 4
b100101 3
b101101 )
b101101 /
b1000 +
b111 -
b111 .
#3501
b111 e
b1100101 \
1%
1#
b111101 5
b1100101 3
#3502
0#
b111110 5
b111 4
#3503
b1000 e
b11100101 \
1%
1#
b111111 5
b11100101 3
#3504
b0 3
b11100101 1
b0 4
#3984
b1000000 5
#4000
1Z
0N
0#
b0 5
b1011 "
b1011 2
0$
b11010 )
b11010 /
b1 *
b1 0
b1001 +
b1 ,
b0 -
b1000 .
#4001
0%
b1 Y
bx1 P
1&
1#
1$
b1 5
b1 3
#4002
0#
0$
b10 5
b1 4
#4003
0!
b10 Y
bx01 P
0&
1#
1$
b11 5
b11 3
#4004
0#
b100 5
b10 4
b1 3
#4005
b11 Y
bx001 P
1#
0$
b101 5
#4006
0#
b110 5
b11 4
#4007
b100 Y
bx0001 P
1#
b111 5
#4008
0#
b1000 5
b100 4
#4009
b101 Y
bx00001 P
1#
b1001 5
#4010
0#
b1010 5
b101 4
#4011
b110 Y
bx000001 P
1#
b1011 5
#4012
0#
b1100 5
b110 4
#4013
1!
b111 Y
bx1000001 P
1&
1#
b1101 5
#4014
0#
b1110 5
b111 4
b1000001 3
#4015
0!
b1000 Y
b1000001 P
0&
1#
b1111 5
b11000001 3
#4016
b1000001 1
b0 4
b0 3
#4496
0#
b10000 5
#4497
b1000000 P
b11011100 O
b1 Y
1#
b10001 5
#4498
0#
b10010 5
b1 4
#4499
b10 Y
1#
b10011 5
#4500
0#
b10100 5
b10 4
b11011 )
b11011 /
b1010 +
b1 -
b1001 .
#4501
1!
b11 Y
b1000100 P
1&
1#
b10101 5
#4502
0#
b10110 5
b11 4
b100 3
#4503
b100 Y
b1001100 P
1&
1#
b10111 5
b1100 3
#4504
0#
b11000 5
b100 4
#4505
b101 Y
b1011100 P
1&
1#
b11001 5
b11100 3
#4506
0#
b11010 5
b101 4
#4507
0!
b110 Y
0&
1#
b11011 5
b111100 3
#4508
0#
b11100 5
b110 4
b11100 3
#4509
1!
b111 Y
1&
1#
b11101 5
#4510
0#
b11110 5
b111 4
b1011100 3
#4511
b1000 Y
b11011100 P
1&
1#
b11111 5
b11011100 3
#4512
b0 3
b11011100 1
b0 4
#4992
0#
b100000 5
#4993
b11011101 P
b111011 O
b1 Y
1&
1#
b100001 5
b1 3
#4994
0#
b100010 5
b1 4
#4995
b10 Y
b11011111 P
1&
1#
b100011 5
b11 3
#4996
0#
b100100 5
b10 4
#4997
0!
b11 Y
b11011011 P
0&
1#
b100101 5
b111 3
#4998
0#
b100110 5
b11 4
b11 3
#4999
1!
b100 Y
1&
1#
b100111 5
#5000
0#
b101000 5
b100 4
b1011 3
b11100 )
b11100 /
b1011 +
b10 -
b1010 .
#5001
b101 Y
1&
1#
b101001 5
b11011 3
#5002
0#
b101010 5
b101 4
#5003
b110 Y
b11111011 P
1&
1#
b101011 5
b111011 3
#5004
0#
b101100 5
b110 4
#5005
0!
b111 Y
b10111011 P
0&
1#
b101101 5
b1111011 3
#5006
0#
b101110 5
b111 4
b111011 3
#5007
b1000 Y
b111011 P
1#
b101111 5
#5008
b0 3
b111011 1
b0 4
#5488
0#
b110000 5
#5489
b111010 P
b1001110 O
b1 Y
1#
b110001 5
#5490
0#
b110010 5
b1 4
#5491
1!
b10 Y
1&
1#
b110011 5
#5492
0#
b110100 5
b10 4
b10 3
#5493
b11 Y
b111110 P
1&
1#
b110101 5
b110 3
#5494
0#
b110110 5
b11 4
#5495
b100 Y
1&
1#
b110111 5
b1110 3
#5496
0#
b111000 5
b100 4
#5497
0!
b101 Y
b101110 P
0&
1#
b111001 5
b11110 3
#5498
0#
b111010 5
b101 4
b1110 3
#5499
b110 Y
b1110 P
1#
b111011 5
#5500
0#
b111100 5
b110 4
b11101 )
b11101 /
b1100 +
b11 -
b1011 .
#5501
1!
b111 Y
b1001110 P
1&
1#
b111101 5
#5502
0#
b111110 5
b111 4
b1001110 3
#5503
0!
b1000 Y
0&
1#
b111111 5
b11001110 3
#5504
b1001110 1
b0 4
b0 3
#5984
b1000000 5
#6000
0#
b0 5
0$
b101010 )
b101010 /
b1101 +
b100 -
b1100 .
#6001
b10001100 O
b1 Y
1#
1$
b1 5
#6002
0#
0$
b10 5
b1 4
#6003
b10 Y
b1001100 P
1#
1$
b11 5
#6004
0#
0$
b100 5
b10 4
#6005
1!
b11 Y
1&
1#
1$
b101 5
#6006
0#
0$
b110 5
b11 4
b100 3
#6007
b100 Y
1&
1#
b111 5
b1100 3
#6008
0#
b1000 5
b100 4
#6009
0!
b101 Y
0&
1#
b1001 5
b11100 3
#6010
0#
b1010 5
b101 4
b1100 3
#6011
b110 Y
1#
b1011 5
#6012
0#
b1100 5
b110 4
#6013
b111 Y
b1100 P
1#
b1101 5
#6014
0#
b1110 5
b111 4
#6015
1!
b1000 Y
b10001100 P
1&
1#
b1111 5
#6016
b10001100 1
b0 4
b0 3
#6496
0#
b10000 5
#6497
b10001101 P
b10110101 O
b1 Y
1&
1#
b10001 5
b1 3
#6498
0#
b10010 5
b1 4
#6499
0!
b10 Y
0&
1#
b10011 5
b11 3
#6500
0#
b10100 5
b10 4
b1 3
b101011 )
b101011 /
b1110 +
b101 -
b1101 .
#6501
1!
b11 Y
1&
1#
b10101 5
#6502
0#
b10110 5
b11 4
b101 3
#6503
0!
b100 Y
b10000101 P
0&
1#
b10111 5
b1101 3
#6504
0#
b11000 5
b100 4
b101 3
#6505
1!
b101 Y
b10010101 P
1&
1#
b11001 5
#6506
0#
b11010 5
b101 4
b10101 3
#6507
b110 Y
b10110101 P
1&
1#
b11011 5
b110101 3
#6508
0#
b11100 5
b110 4
#6509
0!
b111 Y
0&
1#
b11101 5
b1110101 3
#6510
0#
b11110 5
b111 4
b110101 3
#6511
1!
b1000 Y
1&
1#
b11111 5
#6512
b10110101 1
b0 4
b0 3
#6992
0#
b100000 5
#6993
b101 O
b1 Y
1&
1#
b100001 5
b1 3
#6994
0#
b100010 5
b1 4
#6995
0!
b10 Y
0&
1#
b100011 5
b11 3
#6996
0#
b100100 5
b10 4
b1 3
#6997
1!
b11 Y
1&
1#
b100101 5
#6998
0#
b100110 5
b11 4
b101 3
#6999
0!
b100 Y
0&
1#
b100111 5
b1101 3
#7000
0#
b101000 5
b100 4
b101 3
b101100 )
b101100 /
b1111 +
b110 -
b1110 .
#7001
b101 Y
b10100101 P
1#
b101001 5
#7002
0#
b101010 5
b101 4
#7003
b110 Y
b10000101 P
1#
b101011 5
#7004
0#
b101100 5
b110 4
#7005
b111 Y
1#
b101101 5
#7006
0#
b101110 5
b111 4
#7007
b1000 Y
b101 P
1#
b101111 5
#7008
b0 3
b101 1
b0 4
#7488
0#
b110000 5
#7489
1!
1&
b11100101 O
b1 Y
1#
b110001 5
#7490
0#
b110010 5
b1 4
b1 3
#7491
0!
b10 Y
0&
1#
b110011 5
b11 3
#7492
0#
b110100 5
b10 4
b1 3
#7493
1!
b11 Y
1&
1#
b110101 5
#7494
0#
b110110 5
b11 4
b101 3
#7495
0!
b100 Y
0&
1#
b110111 5
b1101 3
#7496
0#
b111000 5
b100 4
b101 3
#7497
b101 Y
1#
b111001 5
#7498
0#
b111010 5
b101 4
#7499
1!
b110 Y
b100101 P
1&
1#
b111011 5
#7500
0#
b111100 5
b110 4
b100101 3
b101101 )
b101101 /
b10000 +
b111 -
b1111 .
#7501
b111 Y
b1100101 P
1&
1#
b111101 5
b1100101 3
#7502
0#
b111110 5
b111 4
#7503
b1000 Y
b11100101 P
1&
1#
b111111 5
b11100101 3
#7504
b0 3
b11100101 1
b0 4
#7984
b1000000 5
#8000
1N
0B
0#
b0 5
b1101 "
b1101 2
0$
b11010 )
b11010 /
b10 *
b10 0
b10001 +
b10 ,
b0 -
b10000 .
#8001
0&
b1 M
bx1 D
1'
1#
1$
b1 5
b1 3
#8002
0#
0$
b10 5
b1 4
#8003
0!
b10 M
bx01 D
0'
1#
1$
b11 5
b11 3
#8004
0#
b100 5
b10 4
b1 3
#8005
b11 M
bx001 D
1#
0$
b101 5
#8006
0#
b110 5
b11 4
#8007
b100 M
bx0001 D
1#
b111 5
#8008
0#
b1000 5
b100 4
#8009
b101 M
bx00001 D
1#
b1001 5
#8010
0#
b1010 5
b101 4
#8011
b110 M
bx000001 D
1#
b1011 5
#8012
0#
b1100 5
b110 4
#8013
1!
b111 M
bx1000001 D
1'
1#
b1101 5
#8014
0#
b1110 5
b111 4
b1000001 3
#8015
0!
b1000 M
b1000001 D
0'
1#
b1111 5
b11000001 3
#8016
b1000001 1
b0 4
b0 3
#8496
0#
b10000 5
#8497
b1000000 D
b11011100 C
b1 M
1#
b10001 5
#8498
0#
b10010 5
b1 4
#8499
b10 M
1#
b10011 5
#8500
0#
b10100 5
b10 4
b11011 )
b11011 /
b10010 +
b1 -
b10001 .
#8501
1!
b11 M
b1000100 D
1'
1#
b10101 5
#8502
0#
b10110 5
b11 4
b100 3
#8503
b100 M
b1001100 D
1'
1#
b10111 5
b1100 3
#8504
0#
b11000 5
b100 4
#8505
b101 M
b1011100 D
1'
1#
b11001 5
b11100 3
#8506
0#
b11010 5
b101 4
#8507
0!
b110 M
0'
1#
b11011 5
b111100 3
#8508
0#
b11100 5
b110 4
b11100 3
#8509
1!
b111 M
1'
1#
b11101 5
#8510
0#
b11110 5
b111 4
b1011100 3
#8511
b1000 M
b11011100 D
1'
1#
b11111 5
b11011100 3
#8512
b0 3
b11011100 1
b0 4
#8992
0#
b100000 5
#8993
b11011101 D
b111011 C
b1 M
1'
1#
b100001 5
b1 3
#8994
0#
b100010 5
b1 4
#8995
b10 M
b11011111 D
1'
1#
b100011 5
b11 3
#8996
0#
b100100 5
b10 4
#8997
0!
b11 M
b11011011 D
0'
1#
b100101 5
b111 3
#8998
0#
b100110 5
b11 4
b11 3
#8999
1!
b100 M
1'
1#
b100111 5
#9000
0#
b101000 5
b100 4
b1011 3
b11100 )
b11100 /
b10011 +
b10 -
b10010 .
#9001
b101 M
1'
1#
b101001 5
b11011 3
#9002
0#
b101010 5
b101 4
#9003
b110 M
b11111011 D
1'
1#
b101011 5
b111011 3
#9004
0#
b101100 5
b110 4
#9005
0!
b111 M
b10111011 D
0'
1#
b101101 5
b1111011 3
#9006
0#
b101110 5
b111 4
b111011 3
#9007
b1000 M
b111011 D
1#
b101111 5
#9008
b0 3
b111011 1
b0 4
#9488
0#
b110000 5
#9489
b111010 D
b1001110 C
b1 M
1#
b110001 5
#9490
0#
b110010 5
b1 4
#9491
1!
b10 M
1'
1#
b110011 5
#9492
0#
b110100 5
b10 4
b10 3
#9493
b11 M
b111110 D
1'
1#
b110101 5
b110 3
#9494
0#
b110110 5
b11 4
#9495
b100 M
1'
1#
b110111 5
b1110 3
#9496
0#
b111000 5
b100 4
#9497
0!
b101 M
b101110 D
0'
1#
b111001 5
b11110 3
#9498
0#
b111010 5
b101 4
b1110 3
#9499
b110 M
b1110 D
1#
b111011 5
#9500
0#
b111100 5
b110 4
b11101 )
b11101 /
b10100 +
b11 -
b10011 .
#9501
1!
b111 M
b1001110 D
1'
1#
b111101 5
#9502
0#
b111110 5
b111 4
b1001110 3
#9503
0!
b1000 M
0'
1#
b111111 5
b11001110 3
#9504
b1001110 1
b0 4
b0 3
#9984
b1000000 5
#10000
0#
b0 5
0$
b101010 )
b101010 /
b10101 +
b100 -
b10100 .
#10001
b10001100 C
b1 M
1#
1$
b1 5
#10002
0#
0$
b10 5
b1 4
#10003
b10 M
b1001100 D
1#
1$
b11 5
#10004
0#
0$
b100 5
b10 4
#10005
1!
b11 M
1'
1#
1$
b101 5
#10006
0#
0$
b110 5
b11 4
b100 3
#10007
b100 M
1'
1#
b111 5
b1100 3
#10008
0#
b1000 5
b100 4
#10009
0!
b101 M
0'
1#
b1001 5
b11100 3
#10010
0#
b1010 5
b101 4
b1100 3
#10011
b110 M
1#
b1011 5
#10012
0#
b1100 5
b110 4
#10013
b111 M
b1100 D
1#
b1101 5
#10014
0#
b1110 5
b111 4
#10015
1!
b1000 M
b10001100 D
1'
1#
b1111 5
#10016
b10001100 1
b0 4
b0 3
#10496
0#
b10000 5
#10497
b10001101 D
b10110101 C
b1 M
1'
1#
b10001 5
b1 3
#10498
0#
b10010 5
b1 4
#10499
0!
b10 M
0'
1#
b10011 5
b11 3
#10500
0#
b10100 5
b10 4
b1 3
b101011 )
b101011 /
b10110 +
b101 -
b10101 .
#10501
1!
b11 M
1'
1#
b10101 5
#10502
0#
b10110 5
b11 4
b101 3
#10503
0!
b100 M
b10000101 D
0'
1#
b10111 5
b1101 3
#10504
0#
b11000 5
b100 4
b101 3
